odoo8_addon_product_supplierinfo_discount-8.0.1.0.0.99.dev30-py3.8-nspkg.pth
odoo_addons/product_supplierinfo_discount/README.rst
odoo_addons/product_supplierinfo_discount/__init__.py
odoo_addons/product_supplierinfo_discount/__openerp__.py
odoo_addons/product_supplierinfo_discount/i18n/ca.po
odoo_addons/product_supplierinfo_discount/i18n/de.po
odoo_addons/product_supplierinfo_discount/i18n/el_GR.po
odoo_addons/product_supplierinfo_discount/i18n/es.po
odoo_addons/product_supplierinfo_discount/i18n/es_MX.po
odoo_addons/product_supplierinfo_discount/i18n/es_PE.po
odoo_addons/product_supplierinfo_discount/i18n/fi.po
odoo_addons/product_supplierinfo_discount/i18n/fr.po
odoo_addons/product_supplierinfo_discount/i18n/hr.po
odoo_addons/product_supplierinfo_discount/i18n/it.po
odoo_addons/product_supplierinfo_discount/i18n/nl_NL.po
odoo_addons/product_supplierinfo_discount/i18n/product_supplierinfo_discount.pot
odoo_addons/product_supplierinfo_discount/i18n/pt_BR.po
odoo_addons/product_supplierinfo_discount/i18n/pt_PT.po
odoo_addons/product_supplierinfo_discount/i18n/ro.po
odoo_addons/product_supplierinfo_discount/i18n/ru.po
odoo_addons/product_supplierinfo_discount/i18n/sk.po
odoo_addons/product_supplierinfo_discount/i18n/sl.po
odoo_addons/product_supplierinfo_discount/i18n/tr_TR.po
odoo_addons/product_supplierinfo_discount/i18n/zh_CN.po
odoo_addons/product_supplierinfo_discount/models/__init__.py
odoo_addons/product_supplierinfo_discount/models/procurement_order.py
odoo_addons/product_supplierinfo_discount/models/product_supplierinfo.py
odoo_addons/product_supplierinfo_discount/models/purchase_order.py
odoo_addons/product_supplierinfo_discount/static/description/icon.png
odoo_addons/product_supplierinfo_discount/tests/__init__.py
odoo_addons/product_supplierinfo_discount/tests/test_product_supplierinfo_discount.py
odoo_addons/product_supplierinfo_discount/views/product_supplierinfo_view.xml
odoo8_addon_product_supplierinfo_discount-8.0.1.0.0.99.dev30.dist-info/METADATA
odoo8_addon_product_supplierinfo_discount-8.0.1.0.0.99.dev30.dist-info/WHEEL
odoo8_addon_product_supplierinfo_discount-8.0.1.0.0.99.dev30.dist-info/namespace_packages.txt
odoo8_addon_product_supplierinfo_discount-8.0.1.0.0.99.dev30.dist-info/top_level.txt
odoo8_addon_product_supplierinfo_discount-8.0.1.0.0.99.dev30.dist-info/RECORD
